{
    "0": {},
    "1": {
        "练兵": [
            {
                "练兵": "练"
            }
        ]
    },
    "2": {
        "堪称第一": [
            {
                "堪称第一": "堪称"
            }
        ],
        "实属不易": [
            {
                "实属不易": "实属"
            }
        ]
    },
    "3": {},
    "4": {
        "订机票": [
            {
                "订机票": "订"
            },
            {
                "订票": "订"
            }
        ],
        "订票": [
            {
                "订票": "订"
            }
        ],
        "收费": [
            {
                "收费": "收"
            }
        ],
        "收税": [
            {
                "收税": "收"
            }
        ],
        "收场": [
            {
                "收场": "收"
            }
        ],
        "持枪": [
            {
                "持枪": "持"
            }
        ],
        "提包": [
            {
                "提包": "提"
            }
        ],
        "提行李": [
            {
                "提行李": "提"
            }
        ],
        "提笔": [
            {
                "提笔": "提"
            }
        ],
        "提意见": [
            {
                "提意见": "提"
            }
        ],
        "备用品": [
            {
                "备用品": "备"
            }
        ],
        "执牛耳": [
            {
                "执牛耳": "执"
            }
        ],
        "签名": [
            {
                "签名": "签"
            }
        ],
        "签合同": [
            {
                "签合同": "签"
            }
        ],
        "抄小路": [
            {
                "抄小路": "抄"
            }
        ]
    },
    "5": {
        "想不到": [
            {
                "想不到": "想"
            },
            {
                "想得到": "想"
            }
        ],
        "想开": [
            {
                "想开": "想"
            }
        ],
        "想要": [
            {
                "想要": "想"
            },
            {
                "想知道": "想"
            },
            {
                "想睡": "想"
            }
        ],
        "想得到": [
            {
                "想得到": "想"
            }
        ],
        "想知道": [
            {
                "想知道": "想"
            }
        ],
        "想想": [
            {
                "想想": "想"
            },
            {
                "想好": "想"
            }
        ],
        "想到": [
            {
                "想到": "想"
            }
        ],
        "想起": [
            {
                "想起": "想"
            }
        ],
        "想望": [
            {
                "想望": "想"
            }
        ],
        "想好": [
            {
                "想好": "想"
            }
        ],
        "想来": [
            {
                "想来": "想"
            }
        ],
        "想睡": [
            {
                "想睡": "想"
            }
        ]
    },
    "6": {
        "帮忙": [
            {
                "帮忙": "帮"
            }
        ],
        "帮办": [
            {
                "帮办": "帮"
            }
        ],
        "拿不动": [
            {
                "拿不动": "拿"
            }
        ],
        "抢镜": [
            {
                "抢镜": "抢"
            }
        ],
        "抢镜头": [
            {
                "抢镜头": "抢"
            }
        ],
        "拼车": [
            {
                "拼车": "拼"
            }
        ],
        "赚外快": [
            {
                "赚外快": "赚"
            },
            {
                "赚钱": "赚"
            }
        ],
        "赚钱": [
            {
                "赚钱": "赚"
            }
        ],
        "争高下": [
            {
                "争高下": "争"
            },
            {
                "争高低": "争"
            }
        ],
        "争高低": [
            {
                "争高低": "争"
            }
        ],
        "凑热闹": [
            {
                "凑热闹": "凑"
            }
        ],
        "赔钱": [
            {
                "赔钱": "赔"
            }
        ],
        "赔笑脸": [
            {
                "赔笑脸": "赔"
            }
        ]
    },
    "7": {
        "受命": [
            {
                "受命": "受"
            }
        ],
        "受降": [
            {
                "受降": "受"
            }
        ],
        "受苦": [
            {
                "受苦": "受"
            }
        ],
        "受邀": [
            {
                "受邀": "受"
            }
        ],
        "受罪": [
            {
                "受罪": "受"
            }
        ],
        "分不开身": [
            {
                "分不开身": "分不开"
            }
        ]
    },
    "8": {
        "到位": [
            {
                "到位": "到"
            }
        ],
        "到站": [
            {
                "到站": "到"
            }
        ],
        "到时候": [
            {
                "到时候": "到"
            }
        ],
        "到处": [
            {
                "到处": "到"
            }
        ]
    },
    "9": {},
    "10": {
        "散发香味": [
            {
                "散发香味": "散发"
            },
            {
                "散发气味": "散发"
            }
        ],
        "散发气味": [
            {
                "散发气味": "散发"
            }
        ]
    },
    "11": {
        "盖章": [
            {
                "盖章": "盖"
            }
        ],
        "盖菜": [
            {
                "盖菜": "盖"
            }
        ],
        "盖上": [
            {
                "盖上": "盖"
            }
        ]
    },
    "12": {},
    "13": {
        "招待所": [
            {
                "招待所": "招待"
            }
        ]
    },
    "14": {
        "喊声": [
            {
                "喊声": "喊"
            }
        ],
        "唠家常": [
            {
                "唠家常": "唠"
            }
        ]
    },
    "15": {
        "撞车": [
            {
                "撞车": "撞"
            }
        ]
    },
    "16": {
        "选种": [
            {
                "选种": "选"
            }
        ],
        "讲诚信": [
            {
                "讲诚信": "讲"
            }
        ],
        "讲话": [
            {
                "讲话": "讲"
            }
        ],
        "讲价钱": [
            {
                "讲价钱": "讲"
            }
        ],
        "讲故事": [
            {
                "讲故事": "讲"
            }
        ],
        "派用场": [
            {
                "派用场": "派"
            }
        ],
        "谈恋爱": [
            {
                "谈恋爱": "谈"
            }
        ]
    },
    "17": {
        "吸取教训": [
            {
                "吸取教训": "吸取"
            }
        ]
    },
    "18": {},
    "19": {
        "超过预期": [
            {
                "超过预期": "超过"
            },
            {
                "超出预期": "超出"
            }
        ],
        "达到目的": [
            {
                "达到目的": "达到"
            }
        ],
        "超出预期": [
            {
                "超出预期": "超出"
            }
        ]
    },
    "20": {
        "镶嵌玻璃": [
            {
                "镶嵌玻璃": "镶嵌"
            }
        ]
    },
    "21": {
        "洗手": [
            {
                "洗手": "洗"
            }
        ],
        "洗澡": [
            {
                "洗澡": "洗"
            },
            {
                "洗热水澡": "洗"
            },
            {
                "洗脸": "洗"
            },
            {
                "泡澡": "泡"
            }
        ],
        "洗热水澡": [
            {
                "洗热水澡": "洗"
            },
            {
                "泡澡": "泡"
            }
        ],
        "洗脸": [
            {
                "洗脸": "洗"
            },
            {
                "泡澡": "泡"
            }
        ],
        "洗碗": [
            {
                "洗碗": "洗"
            }
        ],
        "泡澡": [
            {
                "泡澡": "泡"
            }
        ],
        "泡茶": [
            {
                "泡茶": "泡"
            }
        ],
        "干农活": [
            {
                "干农活": "干"
            }
        ],
        "干事": [
            {
                "干事": "干"
            }
        ],
        "烫嘴": [
            {
                "烫嘴": "烫"
            }
        ]
    },
    "22": {},
    "23": {},
    "24": {
        "参加会议": [
            {
                "参加会议": "参加"
            }
        ],
        "参加比赛": [
            {
                "参加比赛": "参加"
            }
        ],
        "举办音乐会": [
            {
                "举办音乐会": "举办"
            }
        ]
    },
    "25": {
        "镀金属": [
            {
                "镀金属": "镀"
            }
        ]
    },
    "26": {},
    "27": {
        "深化改革": [
            {
                "深化改革": "深化"
            }
        ]
    },
    "28": {
        "充满激情": [
            {
                "充满激情": "充满"
            }
        ],
        "充满信心": [
            {
                "充满信心": "充满"
            }
        ],
        "充满活力": [
            {
                "充满活力": "充满"
            }
        ],
        "毫无吸引力": [
            {
                "毫无吸引力": "毫无"
            }
        ],
        "毫无兴趣": [
            {
                "毫无兴趣": "毫无"
            }
        ]
    },
    "29": {
        "回车": [
            {
                "回车": "回"
            }
        ],
        "回家": [
            {
                "回家": "回"
            }
        ],
        "回头": [
            {
                "回头": "回"
            }
        ],
        "离站": [
            {
                "离站": "离"
            },
            {
                "发车": "发"
            }
        ],
        "换人": [
            {
                "换人": "换"
            }
        ],
        "换车": [
            {
                "换车": "换"
            },
            {
                "转车": "转"
            }
        ],
        "换上": [
            {
                "换上": "换"
            }
        ],
        "换茬": [
            {
                "换茬": "换"
            }
        ],
        "转圈": [
            {
                "转圈": "转"
            }
        ],
        "转车": [
            {
                "转车": "转"
            }
        ],
        "转弯": [
            {
                "转弯": "转"
            }
        ],
        "转转": [
            {
                "转转": "转"
            }
        ],
        "入眼": [
            {
                "入眼": "入"
            }
        ],
        "入肚": [
            {
                "入肚": "入"
            }
        ],
        "入境": [
            {
                "入境": "入"
            }
        ],
        "接人": [
            {
                "接人": "接"
            }
        ],
        "接电话": [
            {
                "接电话": "接"
            },
            {
                "拨电话": "拨"
            }
        ],
        "接站": [
            {
                "接站": "接"
            }
        ],
        "超人": [
            {
                "超人": "超"
            },
            {
                "通人": "通"
            }
        ],
        "发车": [
            {
                "发车": "发"
            }
        ],
        "发财": [
            {
                "发财": "发"
            }
        ],
        "发音": [
            {
                "发音": "发"
            }
        ],
        "定位": [
            {
                "定位": "定"
            }
        ],
        "定点": [
            {
                "定点": "定"
            }
        ],
        "显身手": [
            {
                "显身手": "显"
            }
        ],
        "变红": [
            {
                "变红": "变"
            }
        ],
        "变暗": [
            {
                "变暗": "变"
            }
        ],
        "变脸": [
            {
                "变脸": "变"
            }
        ],
        "变戏法": [
            {
                "变戏法": "变"
            }
        ],
        "变天": [
            {
                "变天": "变"
            }
        ],
        "排队": [
            {
                "排队": "排"
            }
        ],
        "排序": [
            {
                "排序": "排"
            }
        ],
        "照相": [
            {
                "照相": "照"
            },
            {
                "合影": "合"
            }
        ],
        "交好运": [
            {
                "交好运": "交"
            }
        ],
        "交朋友": [
            {
                "交朋友": "交"
            }
        ],
        "合意": [
            {
                "合意": "合"
            }
        ],
        "合胃口": [
            {
                "合胃口": "合"
            }
        ],
        "合影": [
            {
                "合影": "合"
            }
        ],
        "领进": [
            {
                "领进": "领"
            }
        ],
        "遇险": [
            {
                "遇险": "遇"
            }
        ],
        "退钱": [
            {
                "退钱": "退"
            }
        ],
        "退房": [
            {
                "退房": "退"
            }
        ],
        "退票": [
            {
                "退票": "退"
            }
        ],
        "付钱": [
            {
                "付钱": "付"
            }
        ],
        "借镜": [
            {
                "借镜": "借"
            }
        ],
        "改名": [
            {
                "改名": "改"
            }
        ],
        "通人": [
            {
                "通人": "通"
            }
        ],
        "操心": [
            {
                "操心": "操"
            }
        ],
        "试试": [
            {
                "试试": "试"
            },
            {
                "探路": "探"
            }
        ],
        "探路": [
            {
                "探路": "探"
            }
        ],
        "存心": [
            {
                "存心": "存"
            }
        ],
        "充电": [
            {
                "充电": "充"
            }
        ],
        "充公": [
            {
                "充公": "充"
            }
        ],
        "解围": [
            {
                "解围": "解"
            }
        ],
        "招新生": [
            {
                "招新生": "招"
            }
        ],
        "招人": [
            {
                "招人": "招"
            }
        ],
        "投喂": [
            {
                "投喂": "投"
            }
        ],
        "升级": [
            {
                "升级": "升"
            }
        ],
        "调头": [
            {
                "调头": "调"
            }
        ],
        "调色": [
            {
                "调色": "调"
            }
        ],
        "标价": [
            {
                "标价": "标"
            }
        ],
        "动脑筋": [
            {
                "动脑筋": "动"
            }
        ],
        "划分": [
            {
                "划分": "划"
            }
        ],
        "划桨": [
            {
                "划桨": "划"
            }
        ],
        "积德": [
            {
                "积德": "积"
            }
        ],
        "积雪": [
            {
                "积雪": "积"
            }
        ],
        "平山": [
            {
                "平山": "平"
            }
        ],
        "平房": [
            {
                "平房": "平"
            }
        ],
        "拨电话": [
            {
                "拨电话": "拨"
            }
        ]
    },
    "30": {
        "成人": [
            {
                "成人": "成"
            }
        ],
        "成形": [
            {
                "成形": "成"
            }
        ],
        "成事": [
            {
                "成事": "成"
            }
        ],
        "成木乃伊": [
            {
                "成木乃伊": "成"
            }
        ],
        "成天": [
            {
                "成天": "成"
            }
        ]
    },
    "31": {
        "研究会": [
            {
                "研究会": "研究"
            }
        ]
    },
    "32": {
        "走上街头": [
            {
                "走上街头": "走上"
            }
        ],
        "拉开序幕": [
            {
                "拉开序幕": "拉开"
            }
        ]
    },
    "33": {
        "放松身心": [
            {
                "放松身心": "放松"
            }
        ],
        "消磨时间": [
            {
                "消磨时间": "消磨"
            }
        ],
        "放纵自己": [
            {
                "放纵自己": "放纵"
            }
        ],
        "折磨人": [
            {
                "折磨人": "折磨"
            }
        ]
    },
    "34": {
        "静候佳音": [
            {
                "静候佳音": "静候"
            }
        ]
    },
    "35": {
        "游览区": [
            {
                "游览区": "游览"
            }
        ],
        "游泳": [
            {
                "游泳": "游"
            }
        ]
    },
    "36": {
        "撒欢儿": [
            {
                "撒欢儿": "撒"
            }
        ],
        "熬制": [
            {
                "熬制": "熬"
            }
        ],
        "熬汤": [
            {
                "熬汤": "熬"
            }
        ],
        "淋雨": [
            {
                "淋雨": "淋"
            }
        ]
    },
    "37": {},
    "38": {
        "去除内脏": [
            {
                "去除内脏": "去除"
            }
        ],
        "打扫卫生": [
            {
                "打扫卫生": "打扫"
            }
        ]
    },
    "39": {},
    "40": {},
    "41": {},
    "42": {
        "劝说": [
            {
                "劝说": "劝"
            }
        ]
    },
    "43": {
        "做针线活": [
            {
                "做针线活": "做"
            }
        ],
        "做生意": [
            {
                "做生意": "做"
            },
            {
                "做事": "做"
            }
        ],
        "做人": [
            {
                "做人": "做"
            }
        ],
        "做生日": [
            {
                "做生日": "做"
            }
        ],
        "做客": [
            {
                "做客": "做"
            }
        ],
        "做爱": [
            {
                "做爱": "做"
            }
        ],
        "做事": [
            {
                "做事": "做"
            }
        ],
        "做弥撒": [
            {
                "做弥撒": "做"
            }
        ],
        "做游戏": [
            {
                "做游戏": "做"
            }
        ],
        "做手脚": [
            {
                "做手脚": "做"
            }
        ],
        "做梦": [
            {
                "做梦": "做"
            }
        ],
        "做广告": [
            {
                "做广告": "做"
            }
        ],
        "做强": [
            {
                "做强": "做"
            }
        ],
        "做菜": [
            {
                "做菜": "做"
            }
        ],
        "做朋友": [
            {
                "做朋友": "做"
            }
        ],
        "做文章": [
            {
                "做文章": "做"
            }
        ]
    },
    "44": {
        "就是说": [
            {
                "就是说": "就是"
            },
            {
                "即使": "即"
            }
        ],
        "就是了": [
            {
                "就是了": "就是"
            }
        ],
        "即是": [
            {
                "即是": "即"
            },
            {
                "即为": "即"
            }
        ],
        "即使": [
            {
                "即使": "即"
            }
        ],
        "即为": [
            {
                "即为": "即"
            },
            {
                "乃是": "乃"
            }
        ],
        "即位": [
            {
                "即位": "即"
            }
        ],
        "乃是": [
            {
                "乃是": "乃"
            }
        ]
    },
    "45": {
        "浪费金钱": [
            {
                "浪费金钱": "浪费"
            }
        ],
        "浪费时间": [
            {
                "浪费时间": "浪费"
            }
        ],
        "耗费时间": [
            {
                "耗费时间": "耗费"
            }
        ]
    },
    "46": {
        "居里": [
            {
                "居里": "居"
            }
        ],
        "位居榜首": [
            {
                "位居榜首": "位居"
            },
            {
                "名列第一": "名列"
            }
        ],
        "名列第一": [
            {
                "名列第一": "名列"
            }
        ]
    },
    "47": {
        "切入口": [
            {
                "切入口": "切"
            }
        ]
    },
    "48": {
        "保持距离": [
            {
                "保持距离": "保持"
            }
        ],
        "保持安静": [
            {
                "保持安静": "保持"
            }
        ],
        "保持沉默": [
            {
                "保持沉默": "保持"
            }
        ],
        "保持中立": [
            {
                "保持中立": "保持"
            }
        ],
        "保持稳定": [
            {
                "保持稳定": "保持"
            }
        ],
        "保持低调": [
            {
                "保持低调": "保持"
            }
        ],
        "产生热量": [
            {
                "产生热量": "产生"
            }
        ],
        "引起反感": [
            {
                "引起反感": "引起"
            }
        ],
        "维持秩序": [
            {
                "维持秩序": "维持"
            }
        ],
        "维持生计": [
            {
                "维持生计": "维持"
            }
        ],
        "排除在外": [
            {
                "排除在外": "排除"
            }
        ]
    },
    "49": {
        "修路": [
            {
                "修路": "修"
            }
        ],
        "砌墙": [
            {
                "砌墙": "砌"
            }
        ]
    },
    "50": {
        "出入境": [
            {
                "出入境": "出入"
            }
        ],
        "托运行李": [
            {
                "托运行李": "托运"
            }
        ]
    },
    "51": {
        "办理手续": [
            {
                "办理手续": "办理"
            }
        ],
        "申请护照": [
            {
                "申请护照": "申请"
            }
        ]
    },
    "52": {},
    "53": {},
    "54": {},
    "55": {},
    "56": {},
    "57": {
        "分割开来": [
            {
                "分割开来": "分割"
            }
        ]
    },
    "58": {},
    "59": {
        "露出地表": [
            {
                "露出地表": "露出"
            }
        ],
        "举起右手": [
            {
                "举起右手": "举起"
            }
        ],
        "竖起大拇指": [
            {
                "竖起大拇指": "竖起"
            }
        ]
    },
    "60": {},
    "61": {},
    "62": {},
    "63": {
        "签订合同": [
            {
                "签订合同": "签订"
            }
        ]
    },
    "64": {},
    "65": {
        "炒米粉": [
            {
                "炒米粉": "炒"
            },
            {
                "炒菜": "炒"
            },
            {
                "炒鸡蛋": "炒"
            },
            {
                "炒油菜": "炒"
            },
            {
                "蒸蟹": "蒸"
            },
            {
                "煎饼": "煎"
            },
            {
                "煎鱼": "煎"
            },
            {
                "清蒸鱼": "清蒸"
            }
        ],
        "炒菜": [
            {
                "炒菜": "炒"
            },
            {
                "炒鸡蛋": "炒"
            },
            {
                "炒油菜": "炒"
            },
            {
                "蒸蟹": "蒸"
            },
            {
                "煎饼": "煎"
            },
            {
                "煎鱼": "煎"
            },
            {
                "清蒸鱼": "清蒸"
            }
        ],
        "炒鸡蛋": [
            {
                "炒鸡蛋": "炒"
            },
            {
                "炒油菜": "炒"
            },
            {
                "蒸蟹": "蒸"
            },
            {
                "煎饼": "煎"
            },
            {
                "煎鱼": "煎"
            },
            {
                "清蒸鱼": "清蒸"
            }
        ],
        "炒油菜": [
            {
                "炒油菜": "炒"
            },
            {
                "蒸蟹": "蒸"
            },
            {
                "煎饼": "煎"
            },
            {
                "煎鱼": "煎"
            },
            {
                "清蒸鱼": "清蒸"
            }
        ],
        "蒸蟹": [
            {
                "蒸蟹": "蒸"
            },
            {
                "煎饼": "煎"
            },
            {
                "煎鱼": "煎"
            },
            {
                "清蒸鱼": "清蒸"
            }
        ],
        "煎饼": [
            {
                "煎饼": "煎"
            },
            {
                "煎鱼": "煎"
            },
            {
                "清蒸鱼": "清蒸"
            }
        ],
        "煎鱼": [
            {
                "煎鱼": "煎"
            },
            {
                "清蒸鱼": "清蒸"
            }
        ],
        "清蒸鱼": [
            {
                "清蒸鱼": "清蒸"
            }
        ]
    },
    "66": {},
    "67": {},
    "68": {
        "压倒一切": [
            {
                "压倒一切": "压倒"
            }
        ]
    },
    "69": {
        "踩点": [
            {
                "踩点": "踩"
            }
        ],
        "踩高跷": [
            {
                "踩高跷": "踩"
            }
        ],
        "扯后腿": [
            {
                "扯后腿": "扯"
            }
        ],
        "蹬腿": [
            {
                "蹬腿": "蹬"
            }
        ]
    },
    "70": {},
    "71": {
        "调节温度": [
            {
                "调节温度": "调节"
            }
        ]
    },
    "72": {},
    "73": {},
    "74": {
        "赏雪": [
            {
                "赏雪": "赏"
            }
        ],
        "生气": [
            {
                "生气": "生"
            }
        ]
    },
    "75": {
        "吃苦": [
            {
                "吃苦": "吃"
            }
        ],
        "吃得下": [
            {
                "吃得下": "吃"
            }
        ],
        "吃败仗": [
            {
                "吃败仗": "吃"
            }
        ],
        "吃苦头": [
            {
                "吃苦头": "吃"
            },
            {
                "吃亏": "吃"
            }
        ],
        "吃亏": [
            {
                "吃亏": "吃"
            }
        ],
        "吃食": [
            {
                "吃食": "吃"
            },
            {
                "吃饭": "吃"
            },
            {
                "吃零食": "吃"
            },
            {
                "吃快餐": "吃"
            }
        ],
        "吃饭": [
            {
                "吃饭": "吃"
            },
            {
                "吃零食": "吃"
            },
            {
                "吃快餐": "吃"
            }
        ],
        "吃药": [
            {
                "吃药": "吃"
            }
        ],
        "吃香": [
            {
                "吃香": "吃"
            }
        ],
        "吃零食": [
            {
                "吃零食": "吃"
            },
            {
                "吃夜宵": "吃"
            },
            {
                "吃快餐": "吃"
            }
        ],
        "吃火锅": [
            {
                "吃火锅": "吃"
            }
        ],
        "吃夜宵": [
            {
                "吃夜宵": "吃"
            }
        ],
        "吃豆腐": [
            {
                "吃豆腐": "吃"
            }
        ],
        "吃上": [
            {
                "吃上": "吃"
            }
        ],
        "吃快餐": [
            {
                "吃快餐": "吃"
            }
        ]
    },
    "76": {},
    "77": {
        "要人": [
            {
                "要人": "要"
            }
        ],
        "要害处": [
            {
                "要害处": "要"
            }
        ],
        "要事": [
            {
                "要事": "要"
            }
        ],
        "要饭": [
            {
                "要饭": "要"
            }
        ],
        "要点": [
            {
                "要点": "要"
            }
        ],
        "有失偏颇": [
            {
                "有失偏颇": "有失"
            }
        ]
    },
    "78": {
        "尝尝": [
            {
                "尝尝": "尝"
            },
            {
                "尝尝鲜": "尝"
            },
            {
                "尝鲜": "尝"
            }
        ],
        "尝尝鲜": [
            {
                "尝尝鲜": "尝"
            },
            {
                "尝鲜": "尝"
            }
        ],
        "尝鲜": [
            {
                "尝鲜": "尝"
            }
        ],
        "醉蟹": [
            {
                "醉蟹": "醉"
            }
        ]
    },
    "79": {
        "禁止吸烟": [
            {
                "禁止吸烟": "禁止"
            }
        ]
    },
    "80": {
        "感到惊讶": [
            {
                "感到惊讶": "感到"
            }
        ],
        "感到骄傲": [
            {
                "感到骄傲": "感到"
            }
        ],
        "不无道理": [
            {
                "不无道理": "不无"
            }
        ]
    },
    "81": {
        "开船": [
            {
                "开船": "开"
            },
            {
                "开车": "开"
            }
        ],
        "开线": [
            {
                "开线": "开"
            }
        ],
        "开路": [
            {
                "开路": "开"
            }
        ],
        "开头": [
            {
                "开头": "开"
            }
        ],
        "开玩笑": [
            {
                "开玩笑": "开"
            }
        ],
        "开口": [
            {
                "开口": "开"
            }
        ],
        "开价": [
            {
                "开价": "开"
            }
        ],
        "开门": [
            {
                "开门": "开"
            }
        ],
        "开房间": [
            {
                "开房间": "开"
            }
        ],
        "开花": [
            {
                "开花": "开"
            }
        ],
        "开天窗": [
            {
                "开天窗": "开"
            }
        ],
        "开空调": [
            {
                "开空调": "开"
            }
        ],
        "开间": [
            {
                "开间": "开"
            }
        ],
        "开车": [
            {
                "开车": "开"
            }
        ],
        "开药": [
            {
                "开药": "开"
            }
        ]
    },
    "82": {
        "爱戴": [
            {
                "爱戴": "爱"
            }
        ],
        "爱吃": [
            {
                "爱吃": "爱"
            }
        ],
        "爱祖国": [
            {
                "爱祖国": "爱"
            }
        ]
    },
    "83": {},
    "84": {
        "让路": [
            {
                "让路": "让"
            }
        ],
        "让开": [
            {
                "让开": "让"
            }
        ],
        "让给": [
            {
                "让给": "让"
            }
        ],
        "希望渺茫": [
            {
                "希望渺茫": "希望"
            }
        ]
    },
    "85": {
        "表示赞同": [
            {
                "表示赞同": "表示"
            }
        ]
    },
    "86": {},
    "87": {
        "烤乳猪": [
            {
                "烤乳猪": "烤"
            },
            {
                "烤鱼": "烤"
            },
            {
                "炸鱼": "炸"
            },
            {
                "炸春卷": "炸"
            },
            {
                "炸大虾": "炸"
            }
        ],
        "烤鱼": [
            {
                "烤鱼": "烤"
            },
            {
                "炸鱼": "炸"
            },
            {
                "炸春卷": "炸"
            },
            {
                "炸大虾": "炸"
            }
        ],
        "炸鱼": [
            {
                "炸鱼": "炸"
            },
            {
                "炸春卷": "炸"
            },
            {
                "炸大虾": "炸"
            }
        ],
        "炸春卷": [
            {
                "炸春卷": "炸"
            },
            {
                "炸大虾": "炸"
            }
        ],
        "炸大虾": [
            {
                "炸大虾": "炸"
            }
        ]
    },
    "88": {
        "带走": [
            {
                "带走": "带"
            }
        ],
        "带回家": [
            {
                "带回家": "带"
            }
        ],
        "带来": [
            {
                "带来": "带"
            }
        ],
        "呈弧形": [
            {
                "呈弧形": "呈"
            },
            {
                "呈拱形": "呈"
            }
        ],
        "呈拱形": [
            {
                "呈拱形": "呈"
            }
        ],
        "背包": [
            {
                "背包": "背"
            }
        ],
        "圆梦": [
            {
                "圆梦": "圆"
            }
        ],
        "裂隙": [
            {
                "裂隙": "裂"
            }
        ]
    },
    "89": {
        "任选": [
            {
                "任选": "任"
            }
        ],
        "辞去职务": [
            {
                "辞去职务": "辞去"
            }
        ],
        "当选总统": [
            {
                "当选总统": "当选"
            }
        ]
    },
    "90": {},
    "91": {},
    "92": {
        "吃饱肚子": [
            {
                "吃饱肚子": "吃饱"
            }
        ]
    },
    "93": {},
    "94": {},
    "95": {
        "送人": [
            {
                "送人": "送"
            }
        ]
    },
    "96": {
        "穿衣服": [
            {
                "穿衣服": "穿"
            }
        ]
    },
    "97": {},
    "98": {},
    "99": {
        "见到": [
            {
                "见到": "见"
            },
            {
                "不见踪影": "不见"
            }
        ],
        "不见踪影": [
            {
                "不见踪影": "不见"
            }
        ],
        "修成正果": [
            {
                "修成正果": "修成"
            }
        ],
        "有得一比": [
            {
                "有得一比": "有得"
            }
        ]
    },
    "100": {
        "赴约": [
            {
                "赴约": "赴"
            }
        ]
    },
    "101": {
        "坐飞机": [
            {
                "坐飞机": "坐"
            }
        ],
        "坐火车": [
            {
                "坐火车": "坐"
            }
        ],
        "坐位": [
            {
                "坐位": "坐"
            }
        ],
        "坐车": [
            {
                "坐车": "坐"
            }
        ],
        "坐船": [
            {
                "坐船": "坐"
            }
        ],
        "绕路": [
            {
                "绕路": "绕"
            }
        ],
        "临空": [
            {
                "临空": "临"
            }
        ],
        "牵手": [
            {
                "牵手": "牵"
            }
        ],
        "揽生意": [
            {
                "揽生意": "揽"
            }
        ],
        "览胜": [
            {
                "览胜": "览"
            }
        ]
    },
    "102": {
        "发现自己": [
            {
                "发现自己": "发现"
            }
        ],
        "找工作": [
            {
                "找工作": "找"
            }
        ],
        "迷失方向": [
            {
                "迷失方向": "迷失"
            }
        ]
    },
    "103": {
        "娶老婆": [
            {
                "娶老婆": "娶"
            }
        ]
    },
    "104": {
        "制造麻烦": [
            {
                "制造麻烦": "制造"
            }
        ]
    },
    "105": {},
    "106": {
        "睡懒觉": [
            {
                "睡懒觉": "睡"
            }
        ],
        "睡觉": [
            {
                "睡觉": "睡"
            }
        ],
        "光着膀子": [
            {
                "光着膀子": "光着"
            },
            {
                "光着上身": "光着"
            }
        ],
        "光着上身": [
            {
                "光着上身": "光着"
            }
        ]
    },
    "107": {
        "说起来": [
            {
                "说起来": "说起"
            }
        ]
    },
    "108": {},
    "109": {},
    "110": {},
    "111": {},
    "112": {
        "到达站": [
            {
                "到达站": "到达"
            }
        ],
        "到达时间": [
            {
                "到达时间": "到达"
            }
        ],
        "乘凉": [
            {
                "乘凉": "乘"
            }
        ],
        "乘船": [
            {
                "乘船": "乘"
            }
        ],
        "乘出租车": [
            {
                "乘出租车": "乘"
            },
            {
                "乘车": "乘"
            }
        ],
        "乘车": [
            {
                "乘车": "乘"
            },
            {
                "骑车": "骑"
            },
            {
                "驾车": "驾"
            }
        ],
        "乘飞机": [
            {
                "乘飞机": "乘"
            }
        ],
        "乘地铁": [
            {
                "乘地铁": "乘"
            }
        ],
        "乘火车": [
            {
                "乘火车": "乘"
            }
        ],
        "骑马": [
            {
                "骑马": "骑"
            }
        ],
        "骑车": [
            {
                "骑车": "骑"
            }
        ],
        "驾车": [
            {
                "驾车": "驾"
            }
        ]
    },
    "113": {},
    "114": {
        "变成石头": [
            {
                "变成石头": "变成"
            }
        ],
        "改变本性": [
            {
                "改变本性": "改变"
            }
        ]
    },
    "115": {
        "落地": [
            {
                "落地": "落"
            }
        ],
        "落俗套": [
            {
                "落俗套": "落"
            }
        ],
        "负责任": [
            {
                "负责任": "负"
            }
        ],
        "断根": [
            {
                "断根": "断"
            }
        ],
        "断臂": [
            {
                "断臂": "断"
            }
        ],
        "欠火候": [
            {
                "欠火候": "欠"
            }
        ],
        "伤人": [
            {
                "伤人": "伤"
            }
        ],
        "伤心": [
            {
                "伤心": "伤"
            }
        ],
        "结霜": [
            {
                "结霜": "结"
            },
            {
                "结冰": "结"
            }
        ],
        "结冰": [
            {
                "结冰": "结"
            }
        ],
        "急眼": [
            {
                "急眼": "急"
            }
        ],
        "散工": [
            {
                "散工": "散"
            }
        ],
        "散步": [
            {
                "散步": "散"
            }
        ],
        "流口水": [
            {
                "流口水": "流"
            }
        ],
        "堵车": [
            {
                "堵车": "堵"
            }
        ],
        "失误": [
            {
                "失误": "失"
            }
        ],
        "失联": [
            {
                "失联": "失"
            }
        ],
        "蓄水": [
            {
                "蓄水": "蓄"
            }
        ],
        "褪色": [
            {
                "褪色": "褪"
            }
        ]
    },
    "116": {
        "刻字": [
            {
                "刻字": "刻"
            }
        ]
    },
    "117": {},
    "118": {
        "回到家里": [
            {
                "回到家里": "回到"
            },
            {
                "回到家中": "回到"
            }
        ],
        "回到家中": [
            {
                "回到家中": "回到"
            }
        ],
        "离开码头": [
            {
                "离开码头": "离开"
            }
        ]
    },
    "119": {},
    "120": {
        "怕是": [
            {
                "怕是": "怕"
            }
        ],
        "谢谢你": [
            {
                "谢谢你": "谢谢"
            }
        ],
        "搭错车": [
            {
                "搭错车": "搭错"
            }
        ],
        "管不住嘴": [
            {
                "管不住嘴": "管不住"
            }
        ],
        "做不了主": [
            {
                "做不了主": "做不了"
            }
        ]
    },
    "121": {
        "刷牙": [
            {
                "刷牙": "刷"
            }
        ],
        "刮大风": [
            {
                "刮大风": "刮"
            }
        ],
        "剃光头": [
            {
                "剃光头": "剃"
            }
        ],
        "剪票": [
            {
                "剪票": "剪"
            }
        ]
    },
    "122": {
        "使用说明书": [
            {
                "使用说明书": "使用"
            }
        ],
        "携带方便": [
            {
                "携带方便": "携带"
            }
        ],
        "布置作业": [
            {
                "布置作业": "布置"
            }
        ]
    },
    "123": {},
    "124": {
        "直达车": [
            {
                "直达车": "直达"
            }
        ]
    },
    "125": {
        "玩头": [
            {
                "玩头": "玩"
            }
        ],
        "玩游戏": [
            {
                "玩游戏": "玩"
            }
        ],
        "逛商场": [
            {
                "逛商场": "逛"
            }
        ]
    },
    "126": {},
    "127": {},
    "128": {},
    "129": {
        "留长发": [
            {
                "留长发": "留"
            }
        ],
        "留念": [
            {
                "留念": "留"
            }
        ],
        "留心": [
            {
                "留心": "留"
            }
        ],
        "留影": [
            {
                "留影": "留"
            }
        ]
    },
    "130": {
        "粉碎性骨折": [
            {
                "粉碎性骨折": "粉碎"
            }
        ]
    },
    "131": {},
    "132": {},
    "133": {
        "重整山河": [
            {
                "重整山河": "重整"
            }
        ]
    },
    "134": {
        "写字": [
            {
                "写字": "写"
            }
        ],
        "写道": [
            {
                "写道": "写"
            }
        ],
        "写信": [
            {
                "写信": "写"
            }
        ],
        "作保": [
            {
                "作保": "作"
            }
        ],
        "作词": [
            {
                "作词": "作"
            }
        ],
        "作用": [
            {
                "作用": "作"
            }
        ],
        "作诗": [
            {
                "作诗": "作"
            }
        ],
        "作家": [
            {
                "作家": "作"
            }
        ],
        "发表评论": [
            {
                "发表评论": "发表"
            }
        ],
        "编发短信": [
            {
                "编发短信": "编发"
            }
        ]
    },
    "135": {},
    "136": {
        "救命": [
            {
                "救命": "救"
            }
        ]
    },
    "137": {},
    "138": {
        "加油": [
            {
                "加油": "加"
            }
        ],
        "加车": [
            {
                "加车": "加"
            }
        ],
        "加元": [
            {
                "加元": "加"
            }
        ],
        "放走": [
            {
                "放走": "放"
            }
        ],
        "放歌": [
            {
                "放歌": "放"
            }
        ],
        "放牛": [
            {
                "放牛": "放"
            }
        ],
        "放风筝": [
            {
                "放风筝": "放"
            }
        ],
        "放假": [
            {
                "放假": "放"
            }
        ],
        "放鞭炮": [
            {
                "放鞭炮": "放"
            }
        ],
        "取名": [
            {
                "取名": "取"
            }
        ],
        "取景": [
            {
                "取景": "取"
            }
        ],
        "包饭": [
            {
                "包饭": "包"
            }
        ],
        "包船": [
            {
                "包船": "包"
            }
        ],
        "包饺子": [
            {
                "包饺子": "包"
            }
        ],
        "包车": [
            {
                "包车": "包"
            }
        ],
        "装料": [
            {
                "装料": "装"
            }
        ],
        "添麻烦": [
            {
                "添麻烦": "添"
            }
        ]
    },
    "139": {},
    "140": {},
    "141": {
        "走人": [
            {
                "走人": "走"
            }
        ],
        "走夜路": [
            {
                "走夜路": "走"
            }
        ],
        "走步": [
            {
                "走步": "走"
            }
        ],
        "走风": [
            {
                "走风": "走"
            }
        ],
        "走油": [
            {
                "走油": "走"
            }
        ],
        "走弯路": [
            {
                "走弯路": "走"
            }
        ],
        "走路": [
            {
                "走路": "走"
            }
        ],
        "走捷径": [
            {
                "走捷径": "走"
            }
        ],
        "走道": [
            {
                "走道": "走"
            }
        ]
    },
    "142": {},
    "143": {
        "回归故里": [
            {
                "回归故里": "回归"
            }
        ]
    },
    "144": {},
    "145": {},
    "146": {},
    "147": {},
    "148": {},
    "149": {},
    "150": {
        "无意": [
            {
                "无意": "无"
            }
        ],
        "无限制": [
            {
                "无限制": "无"
            }
        ],
        "无特色": [
            {
                "无特色": "无"
            }
        ],
        "无污染": [
            {
                "无污染": "无"
            }
        ],
        "无上": [
            {
                "无上": "无"
            }
        ],
        "无价值": [
            {
                "无价值": "无"
            }
        ],
        "无差别": [
            {
                "无差别": "无"
            }
        ],
        "不在少数": [
            {
                "不在少数": "不在"
            }
        ],
        "不受限制": [
            {
                "不受限制": "不受"
            }
        ],
        "不受影响": [
            {
                "不受影响": "不受"
            }
        ],
        "以备不时之需": [
            {
                "以备不时之需": "以备"
            }
        ]
    },
    "151": {},
    "152": {
        "令状": [
            {
                "令状": "令"
            }
        ],
        "令人失望": [
            {
                "令人失望": "令人"
            }
        ],
        "令人垂涎": [
            {
                "令人垂涎": "令人"
            }
        ],
        "出乎预料": [
            {
                "出乎预料": "出乎"
            },
            {
                "出乎意料": "出乎"
            }
        ],
        "出乎意料": [
            {
                "出乎意料": "出乎"
            }
        ]
    },
    "153": {
        "留学日本": [
            {
                "留学日本": "留学"
            }
        ]
    },
    "154": {},
    "155": {
        "达不到": [
            {
                "达不到": "达"
            }
        ],
        "达人": [
            {
                "达人": "达"
            }
        ],
        "占优势": [
            {
                "占优势": "占"
            },
            {
                "占上风": "占"
            }
        ],
        "占上风": [
            {
                "占上风": "占"
            }
        ],
        "占地": [
            {
                "占地": "占"
            }
        ]
    },
    "156": {
        "萌芽": [
            {
                "萌芽": "萌"
            }
        ],
        "逗笑": [
            {
                "逗笑": "逗"
            }
        ]
    },
    "157": {
        "遭罪": [
            {
                "遭罪": "遭"
            }
        ],
        "遭到反对": [
            {
                "遭到反对": "遭到"
            }
        ]
    },
    "158": {},
    "159": {
        "破四旧": [
            {
                "破四旧": "破"
            }
        ],
        "袭人": [
            {
                "袭人": "袭"
            }
        ],
        "刹车": [
            {
                "刹车": "刹"
            }
        ]
    },
    "160": {
        "放下心": [
            {
                "放下心": "放下"
            }
        ],
        "失去动力": [
            {
                "失去动力": "失去"
            }
        ],
        "失去生命": [
            {
                "失去生命": "失去"
            }
        ],
        "付出代价": [
            {
                "付出代价": "付出"
            }
        ]
    },
    "161": {
        "算账": [
            {
                "算账": "算"
            }
        ],
        "算算": [
            {
                "算算": "算"
            }
        ],
        "得出结论": [
            {
                "得出结论": "得出"
            }
        ]
    },
    "162": {},
    "163": {},
    "164": {
        "唱歌": [
            {
                "唱歌": "唱"
            }
        ]
    },
    "165": {},
    "166": {
        "融于一体": [
            {
                "融于一体": "融于"
            }
        ]
    },
    "167": {
        "抱大腿": [
            {
                "抱大腿": "抱"
            }
        ],
        "挡道": [
            {
                "挡道": "挡"
            }
        ],
        "握手": [
            {
                "握手": "握"
            },
            {
                "直起腰": "直起"
            }
        ],
        "挥手": [
            {
                "挥手": "挥"
            }
        ],
        "拄拐": [
            {
                "拄拐": "拄"
            }
        ],
        "直起腰": [
            {
                "直起腰": "直起"
            }
        ]
    },
    "168": {},
    "169": {},
    "170": {
        "使劲": [
            {
                "使劲": "使"
            }
        ],
        "使出": [
            {
                "使出": "使"
            }
        ],
        "使尽": [
            {
                "使尽": "使"
            }
        ]
    },
    "171": {
        "介绍人": [
            {
                "介绍人": "介绍"
            }
        ]
    },
    "172": {
        "没有声音": [
            {
                "没有声音": "没有"
            }
        ],
        "没有差别": [
            {
                "没有差别": "没有"
            }
        ],
        "没有胃口": [
            {
                "没有胃口": "没有"
            }
        ],
        "没有勇气": [
            {
                "没有勇气": "没有"
            }
        ],
        "没有问题": [
            {
                "没有问题": "没有"
            }
        ],
        "没有选择": [
            {
                "没有选择": "没有"
            }
        ],
        "没有危险": [
            {
                "没有危险": "没有"
            }
        ],
        "没有把握": [
            {
                "没有把握": "没有"
            }
        ],
        "没有负担": [
            {
                "没有负担": "没有"
            },
            {
                "没有阻碍": "没有"
            }
        ],
        "没有人": [
            {
                "没有人": "没有"
            }
        ],
        "没有必要": [
            {
                "没有必要": "没有"
            }
        ],
        "没有阻碍": [
            {
                "没有阻碍": "没有"
            }
        ],
        "没有空调": [
            {
                "没有空调": "没有"
            }
        ],
        "缺乏信心": [
            {
                "缺乏信心": "缺乏"
            }
        ],
        "扯不上关系": [
            {
                "扯不上关系": "扯不上"
            }
        ]
    },
    "173": {},
    "174": {
        "体验生活": [
            {
                "体验生活": "体验"
            }
        ]
    },
    "175": {},
    "176": {},
    "177": {
        "死伤": [
            {
                "死伤": "死"
            }
        ]
    },
    "178": {},
    "179": {},
    "180": {},
    "181": {
        "嚼不动": [
            {
                "嚼不动": "嚼"
            }
        ],
        "吐丝": [
            {
                "吐丝": "吐"
            }
        ],
        "喘口气": [
            {
                "喘口气": "喘"
            }
        ]
    },
    "182": {},
    "183": {
        "打电话": [
            {
                "打电话": "打"
            },
            {
                "挂电话": "挂"
            }
        ],
        "打折": [
            {
                "打折": "打"
            },
            {
                "打八折": "打"
            },
            {
                "打折扣": "打"
            }
        ],
        "打耳光": [
            {
                "打耳光": "打"
            }
        ],
        "打票": [
            {
                "打票": "打"
            }
        ],
        "打八折": [
            {
                "打八折": "打"
            },
            {
                "打折扣": "打"
            }
        ],
        "打折扣": [
            {
                "打折扣": "打"
            }
        ],
        "打招呼": [
            {
                "打招呼": "打"
            }
        ],
        "打预防针": [
            {
                "打预防针": "打"
            }
        ],
        "打飞机": [
            {
                "打飞机": "打"
            }
        ],
        "打孔": [
            {
                "打孔": "打"
            }
        ],
        "打广告": [
            {
                "打广告": "打"
            }
        ],
        "打车": [
            {
                "打车": "打"
            },
            {
                "搭车": "搭"
            }
        ],
        "打雪仗": [
            {
                "打雪仗": "打"
            }
        ],
        "打前站": [
            {
                "打前站": "打"
            }
        ],
        "打水": [
            {
                "打水": "打"
            }
        ],
        "打仗": [
            {
                "打仗": "打"
            }
        ],
        "打交道": [
            {
                "打交道": "打"
            }
        ],
        "打寒噤": [
            {
                "打寒噤": "打"
            }
        ],
        "打点": [
            {
                "打点": "打"
            }
        ],
        "打主意": [
            {
                "打主意": "打"
            }
        ],
        "打哈欠": [
            {
                "打哈欠": "打"
            }
        ],
        "打结": [
            {
                "打结": "打"
            }
        ],
        "打退堂鼓": [
            {
                "打退堂鼓": "打"
            }
        ],
        "打人": [
            {
                "打人": "打"
            }
        ],
        "搭伙": [
            {
                "搭伙": "搭"
            }
        ],
        "搭车": [
            {
                "搭车": "搭"
            }
        ],
        "搭顺风车": [
            {
                "搭顺风车": "搭"
            }
        ],
        "搭飞机": [
            {
                "搭飞机": "搭"
            }
        ],
        "搭火车": [
            {
                "搭火车": "搭"
            }
        ],
        "搭卖": [
            {
                "搭卖": "搭"
            }
        ],
        "爬坡": [
            {
                "爬坡": "爬"
            }
        ],
        "爬山": [
            {
                "爬山": "爬"
            }
        ],
        "挑担子": [
            {
                "挑担子": "挑"
            }
        ],
        "摆姿势": [
            {
                "摆姿势": "摆"
            }
        ],
        "吹风": [
            {
                "吹风": "吹"
            }
        ],
        "吹牛": [
            {
                "吹牛": "吹"
            }
        ],
        "吹口哨": [
            {
                "吹口哨": "吹"
            }
        ],
        "吹冷风": [
            {
                "吹冷风": "吹"
            },
            {
                "泼冷水": "泼"
            }
        ],
        "挂挡": [
            {
                "挂挡": "挂"
            }
        ],
        "挂电话": [
            {
                "挂电话": "挂"
            }
        ],
        "翻番": [
            {
                "翻番": "翻"
            }
        ],
        "翻白眼": [
            {
                "翻白眼": "翻"
            }
        ],
        "翻天": [
            {
                "翻天": "翻"
            }
        ],
        "翻身": [
            {
                "翻身": "翻"
            }
        ],
        "插队": [
            {
                "插队": "插"
            }
        ],
        "铺柏油": [
            {
                "铺柏油": "铺"
            }
        ],
        "摸头": [
            {
                "摸头": "摸"
            }
        ],
        "泼墨": [
            {
                "泼墨": "泼"
            }
        ],
        "泼冷水": [
            {
                "泼冷水": "泼"
            }
        ],
        "碰面": [
            {
                "碰面": "碰"
            }
        ],
        "碰杯": [
            {
                "碰杯": "碰"
            }
        ],
        "钻空子": [
            {
                "钻空子": "钻"
            }
        ],
        "冒险": [
            {
                "冒险": "冒"
            }
        ],
        "掏钱": [
            {
                "掏钱": "掏"
            }
        ],
        "兑水": [
            {
                "兑水": "兑"
            }
        ]
    },
    "184": {
        "配备有": [
            {
                "配备有": "配备"
            }
        ]
    },
    "185": {
        "买票": [
            {
                "买票": "买"
            }
        ],
        "买东西": [
            {
                "买东西": "买"
            }
        ],
        "买保险": [
            {
                "买保险": "买"
            }
        ],
        "买账": [
            {
                "买账": "买"
            }
        ],
        "卖钱": [
            {
                "卖钱": "卖"
            }
        ],
        "卖点": [
            {
                "卖点": "卖"
            }
        ]
    },
    "186": {},
    "187": {},
    "188": {},
    "189": {
        "画句号": [
            {
                "画句号": "画"
            }
        ],
        "画图": [
            {
                "画图": "画"
            },
            {
                "绘图": "绘"
            }
        ],
        "绘图": [
            {
                "绘图": "绘"
            }
        ]
    },
    "190": {},
    "191": {
        "养鱼": [
            {
                "养鱼": "养"
            }
        ],
        "养蜂": [
            {
                "养蜂": "养"
            }
        ]
    },
    "192": {
        "称为": [
            {
                "称为": "称"
            }
        ],
        "称奇": [
            {
                "称奇": "称"
            }
        ],
        "称是": [
            {
                "称是": "称"
            }
        ],
        "指路": [
            {
                "指路": "指"
            }
        ],
        "指称": [
            {
                "指称": "指"
            }
        ]
    },
    "193": {
        "共享单车": [
            {
                "共享单车": "共享"
            }
        ]
    },
    "194": {
        "掉头": [
            {
                "掉头": "掉"
            }
        ],
        "掉眼泪": [
            {
                "掉眼泪": "掉"
            }
        ],
        "硌脚": [
            {
                "硌脚": "硌"
            }
        ]
    },
    "195": {
        "吸引来": [
            {
                "吸引来": "吸引"
            }
        ]
    },
    "196": {
        "晒太阳": [
            {
                "晒太阳": "晒"
            }
        ],
        "晒台": [
            {
                "晒台": "晒"
            }
        ],
        "晒烟": [
            {
                "晒烟": "晒"
            }
        ],
        "晒图": [
            {
                "晒图": "晒"
            }
        ]
    },
    "197": {
        "听话": [
            {
                "听话": "听"
            }
        ],
        "听说过": [
            {
                "听说过": "听"
            }
        ],
        "听不到": [
            {
                "听不到": "听"
            }
        ],
        "听说": [
            {
                "听说": "听"
            }
        ],
        "听讲": [
            {
                "听讲": "听"
            }
        ],
        "听劝": [
            {
                "听劝": "听"
            }
        ],
        "发出响声": [
            {
                "发出响声": "发出"
            }
        ]
    },
    "198": {
        "成为现实": [
            {
                "成为现实": "成为"
            }
        ],
        "打破沉默": [
            {
                "打破沉默": "打破"
            }
        ],
        "超越时空": [
            {
                "超越时空": "超越"
            }
        ]
    },
    "199": {
        "享誉海内外": [
            {
                "享誉海内外": "享誉"
            }
        ]
    },
    "200": {
        "拍照": [
            {
                "拍照": "拍"
            },
            {
                "拍照片": "拍"
            }
        ],
        "拍照片": [
            {
                "拍照片": "拍"
            }
        ],
        "拍片子": [
            {
                "拍片子": "拍"
            },
            {
                "拍片": "拍"
            },
            {
                "拍电影": "拍"
            }
        ],
        "拍片": [
            {
                "拍片": "拍"
            },
            {
                "拍电影": "拍"
            }
        ],
        "拍手": [
            {
                "拍手": "拍"
            }
        ],
        "拍电影": [
            {
                "拍电影": "拍"
            }
        ],
        "拍外景": [
            {
                "拍外景": "拍"
            }
        ],
        "拍花": [
            {
                "拍花": "拍"
            }
        ]
    },
    "201": {
        "开始意识到": [
            {
                "开始意识到": "开始"
            }
        ],
        "开始是": [
            {
                "开始是": "开始"
            },
            {
                "开始行动": "开始"
            }
        ],
        "开始行动": [
            {
                "开始行动": "开始"
            }
        ],
        "开始营业": [
            {
                "开始营业": "开始"
            }
        ],
        "停止营业": [
            {
                "停止营业": "停止"
            }
        ]
    },
    "202": {},
    "203": {},
    "204": {
        "看做": [
            {
                "看做": "看"
            },
            {
                "看作": "看"
            }
        ],
        "看来": [
            {
                "看来": "看"
            },
            {
                "看情况": "看"
            },
            {
                "看似": "看"
            },
            {
                "看样子": "看"
            }
        ],
        "看新闻": [
            {
                "看新闻": "看"
            }
        ],
        "看电影": [
            {
                "看电影": "看"
            },
            {
                "看电视": "看"
            }
        ],
        "看热闹": [
            {
                "看热闹": "看"
            }
        ],
        "看情况": [
            {
                "看情况": "看"
            },
            {
                "看样子": "看"
            }
        ],
        "看穿": [
            {
                "看穿": "看"
            },
            {
                "看破": "看"
            }
        ],
        "看作": [
            {
                "看作": "看"
            }
        ],
        "看车": [
            {
                "看车": "看"
            }
        ],
        "看不到": [
            {
                "看不到": "看"
            }
        ],
        "看小说": [
            {
                "看小说": "看"
            }
        ],
        "看似": [
            {
                "看似": "看"
            }
        ],
        "看在": [
            {
                "看在": "看"
            }
        ],
        "看破": [
            {
                "看破": "看"
            }
        ],
        "看相": [
            {
                "看相": "看"
            }
        ],
        "看电视": [
            {
                "看电视": "看"
            }
        ],
        "看样子": [
            {
                "看样子": "看"
            }
        ],
        "看家": [
            {
                "看家": "看"
            }
        ],
        "看孩子": [
            {
                "看孩子": "看"
            }
        ],
        "看座": [
            {
                "看座": "看"
            }
        ],
        "想起来": [
            {
                "想起来": "想起"
            }
        ]
    },
    "205": {},
    "206": {},
    "207": {
        "映入眼帘": [
            {
                "映入眼帘": "映入"
            }
        ],
        "回过神": [
            {
                "回过神": "回过"
            }
        ],
        "屏住呼吸": [
            {
                "屏住呼吸": "屏住"
            }
        ],
        "睁大眼睛": [
            {
                "睁大眼睛": "睁大"
            }
        ]
    },
    "208": {},
    "209": {},
    "210": {
        "发生车祸": [
            {
                "发生车祸": "发生"
            }
        ],
        "发生事故": [
            {
                "发生事故": "发生"
            }
        ]
    },
    "211": {},
    "212": {},
    "213": {},
    "214": {
        "拉家常": [
            {
                "拉家常": "拉"
            }
        ],
        "拉票": [
            {
                "拉票": "拉"
            }
        ],
        "拉车": [
            {
                "拉车": "拉"
            }
        ],
        "拉肚子": [
            {
                "拉肚子": "拉"
            }
        ],
        "拉线": [
            {
                "拉线": "拉"
            }
        ],
        "拉手": [
            {
                "拉手": "拉"
            }
        ],
        "拉屎": [
            {
                "拉屎": "拉"
            }
        ],
        "登山": [
            {
                "登山": "登"
            }
        ],
        "立轴": [
            {
                "立轴": "立"
            }
        ],
        "扎根": [
            {
                "扎根": "扎"
            }
        ],
        "露脸": [
            {
                "露脸": "露"
            }
        ],
        "露头": [
            {
                "露头": "露"
            }
        ],
        "戴桂冠": [
            {
                "戴桂冠": "戴"
            }
        ],
        "戴高帽": [
            {
                "戴高帽": "戴"
            }
        ],
        "托福": [
            {
                "托福": "托"
            }
        ],
        "拜拜": [
            {
                "拜拜": "拜"
            }
        ],
        "告别": [
            {
                "告别": "告"
            }
        ],
        "歇口气": [
            {
                "歇口气": "歇"
            }
        ],
        "歇脚": [
            {
                "歇脚": "歇"
            }
        ],
        "纳妾": [
            {
                "纳妾": "纳"
            }
        ],
        "呼声": [
            {
                "呼声": "呼"
            }
        ],
        "饶人": [
            {
                "饶人": "饶"
            }
        ]
    },
    "215": {
        "做好准备": [
            {
                "做好准备": "做好"
            }
        ],
        "办手续": [
            {
                "办手续": "办"
            }
        ],
        "办证": [
            {
                "办证": "办"
            }
        ],
        "办丧事": [
            {
                "办丧事": "办"
            }
        ]
    },
    "216": {},
    "217": {
        "赶飞机": [
            {
                "赶飞机": "赶"
            }
        ],
        "赶火车": [
            {
                "赶火车": "赶"
            }
        ],
        "赶热闹": [
            {
                "赶热闹": "赶"
            }
        ],
        "犯困": [
            {
                "犯困": "犯"
            }
        ],
        "犯错误": [
            {
                "犯错误": "犯"
            }
        ],
        "犯事": [
            {
                "犯事": "犯"
            },
            {
                "认罪": "认"
            }
        ],
        "吓一大跳": [
            {
                "吓一大跳": "吓"
            }
        ],
        "吓一跳": [
            {
                "吓一跳": "吓"
            }
        ],
        "砍价": [
            {
                "砍价": "砍"
            }
        ],
        "认罪": [
            {
                "认罪": "认"
            }
        ],
        "拐弯": [
            {
                "拐弯": "拐"
            }
        ],
        "闯祸": [
            {
                "闯祸": "闯"
            }
        ],
        "逃票": [
            {
                "逃票": "逃"
            }
        ],
        "不成样子": [
            {
                "不成样子": "不成"
            }
        ],
        "罚款": [
            {
                "罚款": "罚"
            }
        ],
        "捕鱼": [
            {
                "捕鱼": "捕"
            }
        ]
    },
    "218": {},
    "219": {},
    "220": {},
    "221": {},
    "222": {},
    "223": {},
    "224": {},
    "225": {
        "做出贡献": [
            {
                "做出贡献": "做出"
            }
        ],
        "享有声誉": [
            {
                "享有声誉": "享有"
            }
        ],
        "取得胜利": [
            {
                "取得胜利": "取得"
            }
        ]
    },
    "226": {
        "饮水": [
            {
                "饮水": "饮"
            }
        ],
        "服苦役": [
            {
                "服苦役": "服"
            }
        ]
    },
    "227": {},
    "228": {
        "售票": [
            {
                "售票": "售"
            }
        ]
    },
    "229": {
        "准备睡觉": [
            {
                "准备睡觉": "准备"
            }
        ],
        "提供服务": [
            {
                "提供服务": "提供"
            }
        ],
        "考虑到": [
            {
                "考虑到": "考虑"
            }
        ],
        "应声": [
            {
                "应声": "应"
            }
        ]
    },
    "230": {},
    "231": {},
    "232": {},
    "233": {
        "吊胃口": [
            {
                "吊胃口": "吊"
            }
        ]
    },
    "234": {
        "说不定": [
            {
                "说不定": "说"
            },
            {
                "说起": "说"
            },
            {
                "说实话": "说"
            },
            {
                "说来": "说"
            }
        ],
        "说好话": [
            {
                "说好话": "说"
            }
        ],
        "说教": [
            {
                "说教": "说"
            }
        ],
        "说出口": [
            {
                "说出口": "说"
            },
            {
                "说出来": "说"
            },
            {
                "说出": "说"
            },
            {
                "说笑": "说"
            }
        ],
        "说穿": [
            {
                "说穿": "说"
            }
        ],
        "说起": [
            {
                "说起": "说"
            },
            {
                "说实话": "说"
            },
            {
                "说来": "说"
            },
            {
                "说到": "说"
            }
        ],
        "说大话": [
            {
                "说大话": "说"
            }
        ],
        "说开": [
            {
                "说开": "说"
            }
        ],
        "说不好": [
            {
                "说不好": "说"
            }
        ],
        "说出来": [
            {
                "说出来": "说"
            },
            {
                "说出": "说"
            },
            {
                "说笑": "说"
            }
        ],
        "说实话": [
            {
                "说实话": "说"
            },
            {
                "说来": "说"
            }
        ],
        "说来": [
            {
                "说来": "说"
            }
        ],
        "说动": [
            {
                "说动": "说"
            }
        ],
        "说到": [
            {
                "说到": "说"
            }
        ],
        "说不来": [
            {
                "说不来": "说"
            }
        ],
        "说废话": [
            {
                "说废话": "说"
            }
        ],
        "说道": [
            {
                "说道": "说"
            }
        ],
        "说出": [
            {
                "说出": "说"
            },
            {
                "说笑": "说"
            }
        ],
        "说唱": [
            {
                "说唱": "说"
            }
        ],
        "说可以": [
            {
                "说可以": "说"
            },
            {
                "说好": "说"
            }
        ],
        "说中文": [
            {
                "说中文": "说"
            }
        ],
        "说话": [
            {
                "说话": "说"
            }
        ],
        "说好": [
            {
                "说好": "说"
            }
        ],
        "说笑": [
            {
                "说笑": "说"
            }
        ],
        "问到": [
            {
                "问到": "问"
            }
        ],
        "请来": [
            {
                "请来": "请"
            }
        ],
        "请问": [
            {
                "请问": "请"
            }
        ],
        "请假": [
            {
                "请假": "请"
            }
        ],
        "听说过": [
            {
                "听说过": "听说"
            }
        ]
    },
    "235": {},
    "236": {},
    "237": {},
    "238": {
        "还有多少": [
            {
                "还有多少": "还有"
            }
        ],
        "如云": [
            {
                "如云": "如"
            }
        ],
        "如旧": [
            {
                "如旧": "如"
            },
            {
                "如初": "如"
            }
        ],
        "如初": [
            {
                "如初": "如"
            }
        ],
        "有着天壤之别": [
            {
                "有着天壤之别": "有着"
            }
        ],
        "具有吸引力": [
            {
                "具有吸引力": "具有"
            }
        ],
        "属地": [
            {
                "属地": "属"
            }
        ],
        "存有戒心": [
            {
                "存有戒心": "存有"
            }
        ]
    },
    "239": {},
    "240": {
        "像是": [
            {
                "像是": "像"
            },
            {
                "看上去好像": "看上去"
            }
        ],
        "像样子": [
            {
                "像样子": "像"
            }
        ],
        "看上去好像": [
            {
                "看上去好像": "看上去"
            }
        ]
    },
    "241": {},
    "242": {},
    "243": {},
    "244": {},
    "245": {
        "结为夫妻": [
            {
                "结为夫妻": "结为"
            }
        ],
        "结为好友": [
            {
                "结为好友": "结为"
            }
        ]
    },
    "246": {},
    "247": {
        "沾光": [
            {
                "沾光": "沾"
            }
        ],
        "喷香": [
            {
                "喷香": "喷"
            }
        ]
    },
    "248": {},
    "249": {
        "出身名门": [
            {
                "出身名门": "出身"
            }
        ]
    }
}